mcp4161/__init__.py
mcp4161/driver.py
mcp4161/py.typed
mcp4161/tests/__init__.py
mcp4161/tests/test_driver.py
mcp4161-0.0.0.dev6.dist-info/LICENSE
mcp4161-0.0.0.dev6.dist-info/METADATA
mcp4161-0.0.0.dev6.dist-info/WHEEL
mcp4161-0.0.0.dev6.dist-info/top_level.txt
mcp4161-0.0.0.dev6.dist-info/RECORD
