Metadata-Version: 2.1
Name: mcp4161
Version: 0.0.0.dev6
Summary: A Python driver for Microchip Technology MCP4161 7/8-Bit Single/Dual SPI Digital POT with Non-Volatile Memory
Home-page: https://github.com/blueskysolarracing/mcp4161
Author: Blue Sky Solar Racing
Author-email: blueskysolar@studentorg.utoronto.ca
License: MIT
Project-URL: Documentation, https://mcp4161.readthedocs.io/en/latest/
Project-URL: Source, https://github.com/blueskysolarracing/mcp4161
Project-URL: Tracker, https://github.com/blueskysolarracing/mcp4161/issues
Keywords: python
Classifier: Development Status :: 5 - Production/Stable
Classifier: Intended Audience :: Developers
Classifier: Intended Audience :: Education
Classifier: Topic :: Education
Classifier: Topic :: Scientific/Engineering
Classifier: License :: OSI Approved :: MIT License
Classifier: Operating System :: OS Independent
Classifier: Programming Language :: Python
Classifier: Programming Language :: Python :: 3
Classifier: Programming Language :: Python :: 3 :: Only
Classifier: Programming Language :: Python :: 3.11
Classifier: Programming Language :: Python :: 3.12
Requires-Python: >=3.11
License-File: LICENSE
Requires-Dist: python-periphery <3,>=2.4.1
